spaceone/__init__.py
spaceone/inventory/__init__.py
spaceone/inventory/api/__init__.py
spaceone/inventory/api/plugin/__init__.py
spaceone/inventory/api/plugin/collector.py
spaceone/inventory/conf/__init__.py
spaceone/inventory/conf/global_conf.py
spaceone/inventory/conf/metric_type_conf.py
spaceone/inventory/conf/proto_conf.py
spaceone/inventory/connector/__init__.py
spaceone/inventory/connector/google_cloud_connector.py
spaceone/inventory/connector/identity_connector.py
spaceone/inventory/connector/inventory_connector.py
spaceone/inventory/connector/monitoring_connector.py
spaceone/inventory/error/__init__.py
spaceone/inventory/error/custom.py
spaceone/inventory/info/__init__.py
spaceone/inventory/info/collector_info.py
spaceone/inventory/info/common_info.py
spaceone/inventory/libs/__init__.py
spaceone/inventory/libs/schema/__init__.py
spaceone/inventory/libs/schema/base.py
spaceone/inventory/libs/schema/cloud_service.py
spaceone/inventory/libs/schema/metric_schema.py
spaceone/inventory/libs/schema/metadata/__init__.py
spaceone/inventory/libs/schema/metadata/dynamic_field.py
spaceone/inventory/libs/schema/metadata/dynamic_layout.py
spaceone/inventory/libs/schema/metadata/dynamic_search.py
spaceone/inventory/manager/__init__.py
spaceone/inventory/manager/google_cloud_manager.py
spaceone/inventory/manager/identity_manager.py
spaceone/inventory/manager/inventory_manager.py
spaceone/inventory/manager/monitoring_manager.py
spaceone/inventory/manager/collector/__init__.py
spaceone/inventory/manager/collector/aws_manager.py
spaceone/inventory/manager/collector/manager.py
spaceone/inventory/model/__init__.py
spaceone/inventory/model/cloud_service.py
spaceone/inventory/model/metric_schema.py
spaceone/inventory/model/server.py
spaceone/inventory/model/metadata/__init__.py
spaceone/inventory/model/metadata/metadata.py
spaceone/inventory/model/metadata/metadata_dynamic_field.py
spaceone/inventory/model/metadata/metadata_dynamic_layout.py
spaceone/inventory/service/__init__.py
plugin_monitoring_metric_collector-1.3.1.dist-info/METADATA
plugin_monitoring_metric_collector-1.3.1.dist-info/WHEEL
plugin_monitoring_metric_collector-1.3.1.dist-info/top_level.txt
plugin_monitoring_metric_collector-1.3.1.dist-info/RECORD
