Metadata-Version: 2.1
Name: plugin-monitoring-metric-collector
Version: 1.3.1
Summary: Collector monitoring data per providers
Home-page: https://www.spaceone.dev/
Author: MEGAZONE SpaceONE Team
Author-email: admin@spaceone.dev
License: Apache License 2.0
Requires-Dist: kt-ds-core
Requires-Dist: kt-ds-api
Requires-Dist: schematics
Requires-Dist: moto
